netsyslog3/__init__.py
netsyslog3/netsyslog3.py
netsyslog3-0.1.2.dist-info/AUTHORS
netsyslog3-0.1.2.dist-info/LICENSE
netsyslog3-0.1.2.dist-info/METADATA
netsyslog3-0.1.2.dist-info/WHEEL
netsyslog3-0.1.2.dist-info/top_level.txt
netsyslog3-0.1.2.dist-info/RECORD
