Metadata-Version: 2.1
Name: netsyslog3
Version: 0.1.2
Summary: Send log messages to remote syslog servers
Home-page: https://github.com/ptrktn/python-netsyslog3
Author: Graham Ashton
Author-email: ashtong@users.sourceforge.net
License: UNKNOWN
Project-URL: Bug Tracker, https://github.com/ptrktn/python-netsyslog3/issues
Platform: UNKNOWN
Classifier: Programming Language :: Python :: 3
Classifier: License :: OSI Approved :: MIT License
Classifier: Operating System :: OS Independent
Requires-Python: >=3.6
License-File: LICENSE
License-File: AUTHORS
